{"cod":"200","message":0.008,"cnt":40,"list":[{"dt":1567015200,"main":{"temp":294.76,"temp_min":293.7,"temp_max":294.76,"pressure":1012.25,"sea_level":1012.25,"grnd_level":1012.25,"humidity":84,"temp_kf":1.06},"weather":[{"id":800,"main":"Clear","description":"clear sky","icon":"01d"}],"clouds":{"all":1},"wind":{"speed":2.37,"deg":278.636},"rain":{},"sys":{"pod":"d"},"dt_txt":"2019-08-28 18:00:00"},{"dt":1567026000,"main":{"temp":293.31,"temp_min":292.514,"temp_max":293.31,"pressure":1013.01,"sea_level":1013.01,"grnd_level":1012.65,"humidity":88,"temp_kf":0.8},"weather":[{"id":804,"main":"Clouds","description":"overcast clouds","icon":"04n"}],"clouds":{"all":100},"wind":{"speed":2.21,"deg":271.348},"sys":{"pod":"n"},"dt_txt":"2019-08-28 21:00:00"},{"dt":1567036800,"main":{"temp":292.3,"temp_min":291.768,"temp_max":292.3,"pressure":1013.68,"sea_level":1013.68,"grnd_level":1013.47,"humidity":91,"temp_kf":0.53},"weather":[{"id":804,"main":"Clouds","description":"overcast clouds","icon":"04n"}],"clouds":{"all":98},"wind":{"speed":2.11,"deg":275.941},"sys":{"pod":"n"},"dt_txt":"2019-08-29 00:00:00"},{"dt":1567047600,"main":{"temp":291.87,"temp_min":291.6,"temp_max":291.87,"pressure":1013.82,"sea_level":1013.82,"grnd_level":1013.7,"humidity":88,"temp_kf":0.27},"weather":[{"id":804,"main":"Clouds","description":"overcast clouds","icon":"04n"}],"clouds":{"all":96},"wind":{"speed":2.84,"deg":256.904},"sys":{"pod":"n"},"dt_txt":"2019-08-29 03:00:00"},{"dt":1567058400,"main":{"temp":291.5,"temp_min":291.5,"temp_max":291.5,"pressure":1014.47,"sea_level":1014.47,"grnd_level":1014.19,"humidity":93,"temp_kf":0},"weather":[{"id":500,"main":"Rain","description":"light rain","icon":"10d"}],"clouds":{"all":98},"wind":{"speed":1.88,"deg":176.285},"rain":{"3h":1.375},"sys":{"pod":"d"},"dt_txt":"2019-08-29 06:00:00"},{"dt":1567069200,"main":{"temp":294.536,"temp_min":294.536,"temp_max":294.536,"pressure":1015.22,"sea_level":1015.22,"grnd_level":1014.97,"humidity":81,"temp_kf":0},"weather":[{"id":500,"main":"Rain","description":"light rain","icon":"10d"}],"clouds":{"all":58},"wind":{"speed":5.76,"deg":235.584},"rain":{"3h":0.375},"sys":{"pod":"d"},"dt_txt":"2019-08-29 09:00:00"},{"dt":1567080000,"main":{"temp":295.232,"temp_min":295.232,"temp_max":295.232,"pressure":1016.16,"sea_level":1016.16,"grnd_level":1015.95,"humidity":68,"temp_kf":0},"weather":[{"id":500,"main":"Rain","description":"light rain","icon":"10d"}],"clouds":{"all":33},"wind":{"speed":6.03,"deg":248.202},"rain":{"3h":0.25},"sys":{"pod":"d"},"dt_txt":"2019-08-29 12:00:00"},{"dt":1567090800,"main":{"temp":293.715,"temp_min":293.715,"temp_max":293.715,"pressure":1016.85,"sea_level":1016.85,"grnd_level":1016.87,"humidity":72,"temp_kf":0},"weather":[{"id":800,"main":"Clear","description":"clear sky","icon":"01d"}],"clouds":{"all":0},"wind":{"speed":5.36,"deg":283.997},"sys":{"pod":"d"},"dt_txt":"2019-08-29 15:00:00"},{"dt":1567101600,"main":{"temp":290.458,"temp_min":290.458,"temp_max":290.458,"pressure":1017.87,"sea_level":1017.87,"grnd_level":1017.84,"humidity":83,"temp_kf":0},"weather":[{"id":800,"main":"Clear","description":"clear sky","icon":"01d"}],"clouds":{"all":8},"wind":{"speed":3.22,"deg":275.895},"sys":{"pod":"d"},"dt_txt":"2019-08-29 18:00:00"},{"dt":1567112400,"main":{"temp":289.556,"temp_min":289.556,"temp_max":289.556,"pressure":1019.18,"sea_level":1019.18,"grnd_level":1018.89,"humidity":84,"temp_kf":0},"weather":[{"id":803,"main":"Clouds","description":"broken clouds","icon":"04n"}],"clouds":{"all":65},"wind":{"speed":2.66,"deg":253.107},"sys":{"pod":"n"},"dt_txt":"2019-08-29 21:00:00"},{"dt":1567123200,"main":{"temp":288.059,"temp_min":288.059,"temp_max":288.059,"pressure":1019.58,"sea_level":1019.58,"grnd_level":1019.29,"humidity":91,"temp_kf":0},"weather":[{"id":802,"main":"Clouds","description":"scattered clouds","icon":"03n"}],"clouds":{"all":47},"wind":{"speed":2.74,"deg":231.304},"sys":{"pod":"n"},"dt_txt":"2019-08-30 00:00:00"},{"dt":1567134000,"main":{"temp":287.8,"temp_min":287.8,"temp_max":287.8,"pressure":1019.72,"sea_level":1019.72,"grnd_level":1019.39,"humidity":93,"temp_kf":0},"weather":[{"id":802,"main":"Clouds","description":"scattered clouds","icon":"03n"}],"clouds":{"all":28},"wind":{"speed":2.51,"deg":213.608},"sys":{"pod":"n"},"dt_txt":"2019-08-30 03:00:00"},{"dt":1567144800,"main":{"temp":289.512,"temp_min":289.512,"temp_max":289.512,"pressure":1020.41,"sea_level":1020.41,"grnd_level":1020.12,"humidity":90,"temp_kf":0},"weather":[{"id":802,"main":"Clouds","description":"scattered clouds","icon":"03d"}],"clouds":{"all":40},"wind":{"speed":2.55,"deg":207.118},"sys":{"pod":"d"},"dt_txt":"2019-08-30 06:00:00"},{"dt":1567155600,"main":{"temp":292.812,"temp_min":292.812,"temp_max":292.812,"pressure":1021.16,"sea_level":1021.16,"grnd_level":1020.86,"humidity":70,"temp_kf":0},"weather":[{"id":804,"main":"Clouds","description":"overcast clouds","icon":"04d"}],"clouds":{"all":100},"wind":{"speed":3.87,"deg":225.535},"sys":{"pod":"d"},"dt_txt":"2019-08-30 09:00:00"},{"dt":1567166400,"main":{"temp":294.6,"temp_min":294.6,"temp_max":294.6,"pressure":1020.88,"sea_level":1020.88,"grnd_level":1020.49,"humidity":56,"temp_kf":0},"weather":[{"id":804,"main":"Clouds","description":"overcast clouds","icon":"04d"}],"clouds":{"all":100},"wind":{"speed":4.03,"deg":227.634},"sys":{"pod":"d"},"dt_txt":"2019-08-30 12:00:00"},{"dt":1567177200,"main":{"temp":293.1,"temp_min":293.1,"temp_max":293.1,"pressure":1020.07,"sea_level":1020.07,"grnd_level":1020.15,"humidity":59,"temp_kf":0},"weather":[{"id":804,"main":"Clouds","description":"overcast clouds","icon":"04d"}],"clouds":{"all":100},"wind":{"speed":3.64,"deg":258.984},"sys":{"pod":"d"},"dt_txt":"2019-08-30 15:00:00"},{"dt":1567188000,"main":{"temp":289.612,"temp_min":289.612,"temp_max":289.612,"pressure":1019.44,"sea_level":1019.44,"grnd_level":1019.35,"humidity":74,"temp_kf":0},"weather":[{"id":804,"main":"Clouds","description":"overcast clouds","icon":"04d"}],"clouds":{"all":100},"wind":{"speed":1.18,"deg":208.928},"sys":{"pod":"d"},"dt_txt":"2019-08-30 18:00:00"},{"dt":1567198800,"main":{"temp":287.225,"temp_min":287.225,"temp_max":287.225,"pressure":1019.55,"sea_level":1019.55,"grnd_level":1019.49,"humidity":81,"temp_kf":0},"weather":[{"id":803,"main":"Clouds","description":"broken clouds","icon":"04n"}],"clouds":{"all":83},"wind":{"speed":1.43,"deg":172.686},"sys":{"pod":"n"},"dt_txt":"2019-08-30 21:00:00"},{"dt":1567209600,"main":{"temp":286.759,"temp_min":286.759,"temp_max":286.759,"pressure":1018.28,"sea_level":1018.28,"grnd_level":1018.14,"humidity":79,"temp_kf":0},"weather":[{"id":804,"main":"Clouds","description":"overcast clouds","icon":"04n"}],"clouds":{"all":89},"wind":{"speed":2.76,"deg":151.272},"sys":{"pod":"n"},"dt_txt":"2019-08-31 00:00:00"},{"dt":1567220400,"main":{"temp":286.2,"temp_min":286.2,"temp_max":286.2,"pressure":1016.54,"sea_level":1016.54,"grnd_level":1016.43,"humidity":85,"temp_kf":0},"weather":[{"id":804,"main":"Clouds","description":"overcast clouds","icon":"04n"}],"clouds":{"all":100},"wind":{"speed":3.07,"deg":164.968},"sys":{"pod":"n"},"dt_txt":"2019-08-31 03:00:00"},{"dt":1567231200,"main":{"temp":288.273,"temp_min":288.273,"temp_max":288.273,"pressure":1015.19,"sea_level":1015.19,"grnd_level":1015.25,"humidity":90,"temp_kf":0},"weather":[{"id":803,"main":"Clouds","description":"broken clouds","icon":"04d"}],"clouds":{"all":67},"wind":{"speed":3.23,"deg":171.935},"sys":{"pod":"d"},"dt_txt":"2019-08-31 06:00:00"},{"dt":1567242000,"main":{"temp":294.671,"temp_min":294.671,"temp_max":294.671,"pressure":1014.07,"sea_level":1014.07,"grnd_level":1014.15,"humidity":58,"temp_kf":0},"weather":[{"id":801,"main":"Clouds","description":"few clouds","icon":"02d"}],"clouds":{"all":16},"wind":{"speed":3.41,"deg":188.111},"sys":{"pod":"d"},"dt_txt":"2019-08-31 09:00:00"},{"dt":1567252800,"main":{"temp":297.6,"temp_min":297.6,"temp_max":297.6,"pressure":1011.88,"sea_level":1011.88,"grnd_level":1011.82,"humidity":51,"temp_kf":0},"weather":[{"id":800,"main":"Clear","description":"clear sky","icon":"01d"}],"clouds":{"all":9},"wind":{"speed":3.6,"deg":192.363},"sys":{"pod":"d"},"dt_txt":"2019-08-31 12:00:00"},{"dt":1567263600,"main":{"temp":298.617,"temp_min":298.617,"temp_max":298.617,"pressure":1009.55,"sea_level":1009.55,"grnd_level":1008.77,"humidity":58,"temp_kf":0},"weather":[{"id":500,"main":"Rain","description":"light rain","icon":"10d"}],"clouds":{"all":18},"wind":{"speed":4.02,"deg":194.226},"rain":{"3h":0.062},"sys":{"pod":"d"},"dt_txt":"2019-08-31 15:00:00"},{"dt":1567274400,"main":{"temp":293.51,"temp_min":293.51,"temp_max":293.51,"pressure":1007.77,"sea_level":1007.77,"grnd_level":1007.47,"humidity":78,"temp_kf":0},"weather":[{"id":801,"main":"Clouds","description":"few clouds","icon":"02d"}],"clouds":{"all":18},"wind":{"speed":1.74,"deg":240.615},"rain":{},"sys":{"pod":"d"},"dt_txt":"2019-08-31 18:00:00"},{"dt":1567285200,"main":{"temp":291.536,"temp_min":291.536,"temp_max":291.536,"pressure":1006.1,"sea_level":1006.1,"grnd_level":1005.99,"humidity":82,"temp_kf":0},"weather":[{"id":803,"main":"Clouds","description":"broken clouds","icon":"04n"}],"clouds":{"all":52},"wind":{"speed":2.91,"deg":157.083},"sys":{"pod":"n"},"dt_txt":"2019-08-31 21:00:00"},{"dt":1567296000,"main":{"temp":291.036,"temp_min":291.036,"temp_max":291.036,"pressure":1004.13,"sea_level":1004.13,"grnd_level":1003.95,"humidity":71,"temp_kf":0},"weather":[{"id":803,"main":"Clouds","description":"broken clouds","icon":"04n"}],"clouds":{"all":54},"wind":{"speed":3.63,"deg":177.633},"sys":{"pod":"n"},"dt_txt":"2019-09-01 00:00:00"},{"dt":1567306800,"main":{"temp":291.5,"temp_min":291.5,"temp_max":291.5,"pressure":1003.91,"sea_level":1003.91,"grnd_level":1003.62,"humidity":79,"temp_kf":0},"weather":[{"id":804,"main":"Clouds","description":"overcast clouds","icon":"04n"}],"clouds":{"all":100},"wind":{"speed":5.56,"deg":262.783},"sys":{"pod":"n"},"dt_txt":"2019-09-01 03:00:00"},{"dt":1567317600,"main":{"temp":290.4,"temp_min":290.4,"temp_max":290.4,"pressure":1005.58,"sea_level":1005.58,"grnd_level":1005.09,"humidity":80,"temp_kf":0},"weather":[{"id":500,"main":"Rain","description":"light rain","icon":"10d"}],"clouds":{"all":100},"wind":{"speed":7.17,"deg":279.58},"rain":{"3h":0.188},"sys":{"pod":"d"},"dt_txt":"2019-09-01 06:00:00"},{"dt":1567328400,"main":{"temp":291.125,"temp_min":291.125,"temp_max":291.125,"pressure":1007.73,"sea_level":1007.73,"grnd_level":1007.3,"humidity":60,"temp_kf":0},"weather":[{"id":804,"main":"Clouds","description":"overcast clouds","icon":"04d"}],"clouds":{"all":100},"wind":{"speed":7.32,"deg":271.354},"sys":{"pod":"d"},"dt_txt":"2019-09-01 09:00:00"},{"dt":1567339200,"main":{"temp":290.61,"temp_min":290.61,"temp_max":290.61,"pressure":1009.13,"sea_level":1009.13,"grnd_level":1008.98,"humidity":63,"temp_kf":0},"weather":[{"id":500,"main":"Rain","description":"light rain","icon":"10d"}],"clouds":{"all":100},"wind":{"speed":6.41,"deg":260.219},"rain":{"3h":0.313},"sys":{"pod":"d"},"dt_txt":"2019-09-01 12:00:00"},{"dt":1567350000,"main":{"temp":290.9,"temp_min":290.9,"temp_max":290.9,"pressure":1009.33,"sea_level":1009.33,"grnd_level":1009.1,"humidity":59,"temp_kf":0},"weather":[{"id":500,"main":"Rain","description":"light rain","icon":"10d"}],"clouds":{"all":67},"wind":{"speed":6.25,"deg":255.806},"rain":{"3h":0.25},"sys":{"pod":"d"},"dt_txt":"2019-09-01 15:00:00"},{"dt":1567360800,"main":{"temp":287.8,"temp_min":287.8,"temp_max":287.8,"pressure":1009.71,"sea_level":1009.71,"grnd_level":1009.32,"humidity":73,"temp_kf":0},"weather":[{"id":500,"main":"Rain","description":"light rain","icon":"10d"}],"clouds":{"all":33},"wind":{"speed":4.73,"deg":241.163},"rain":{"3h":0.25},"sys":{"pod":"d"},"dt_txt":"2019-09-01 18:00:00"},{"dt":1567371600,"main":{"temp":286.695,"temp_min":286.695,"temp_max":286.695,"pressure":1010.54,"sea_level":1010.54,"grnd_level":1010.04,"humidity":73,"temp_kf":0},"weather":[{"id":800,"main":"Clear","description":"clear sky","icon":"01n"}],"clouds":{"all":0},"wind":{"speed":4.55,"deg":237.034},"sys":{"pod":"n"},"dt_txt":"2019-09-01 21:00:00"},{"dt":1567382400,"main":{"temp":285.921,"temp_min":285.921,"temp_max":285.921,"pressure":1010.49,"sea_level":1010.49,"grnd_level":1009.92,"humidity":74,"temp_kf":0},"weather":[{"id":800,"main":"Clear","description":"clear sky","icon":"01n"}],"clouds":{"all":0},"wind":{"speed":4.31,"deg":218.996},"sys":{"pod":"n"},"dt_txt":"2019-09-02 00:00:00"},{"dt":1567393200,"main":{"temp":285.571,"temp_min":285.571,"temp_max":285.571,"pressure":1010.07,"sea_level":1010.07,"grnd_level":1009.4,"humidity":81,"temp_kf":0},"weather":[{"id":500,"main":"Rain","description":"light rain","icon":"10n"}],"clouds":{"all":0},"wind":{"speed":4.3,"deg":216.222},"rain":{"3h":0.5},"sys":{"pod":"n"},"dt_txt":"2019-09-02 03:00:00"},{"dt":1567404000,"main":{"temp":286.485,"temp_min":286.485,"temp_max":286.485,"pressure":1010.29,"sea_level":1010.29,"grnd_level":1009.63,"humidity":84,"temp_kf":0},"weather":[{"id":500,"main":"Rain","description":"light rain","icon":"10d"}],"clouds":{"all":21},"wind":{"speed":4.63,"deg":211.836},"rain":{"3h":1.188},"sys":{"pod":"d"},"dt_txt":"2019-09-02 06:00:00"},{"dt":1567414800,"main":{"temp":288.619,"temp_min":288.619,"temp_max":288.619,"pressure":1010.39,"sea_level":1010.39,"grnd_level":1009.84,"humidity":74,"temp_kf":0},"weather":[{"id":501,"main":"Rain","description":"moderate rain","icon":"10d"}],"clouds":{"all":92},"wind":{"speed":6.58,"deg":218.464},"rain":{"3h":3.562},"sys":{"pod":"d"},"dt_txt":"2019-09-02 09:00:00"},{"dt":1567425600,"main":{"temp":289.1,"temp_min":289.1,"temp_max":289.1,"pressure":1010.08,"sea_level":1010.08,"grnd_level":1009.81,"humidity":70,"temp_kf":0},"weather":[{"id":500,"main":"Rain","description":"light rain","icon":"10d"}],"clouds":{"all":86},"wind":{"speed":6.34,"deg":234.293},"rain":{"3h":2.188},"sys":{"pod":"d"},"dt_txt":"2019-09-02 12:00:00"},{"dt":1567436400,"main":{"temp":288,"temp_min":288,"temp_max":288,"pressure":1010.14,"sea_level":1010.14,"grnd_level":1009.84,"humidity":74,"temp_kf":0},"weather":[{"id":500,"main":"Rain","description":"light rain","icon":"10d"}],"clouds":{"all":95},"wind":{"speed":5.05,"deg":238.074},"rain":{"3h":2.312},"sys":{"pod":"d"},"dt_txt":"2019-09-02 15:00:00"}],"city":{"id":2897132,"name":"Husum","coord":{"lat":54.4858,"lon":9.0524},"country":"DE","timezone":7200,"sunrise":1566966193,"sunset":1567016852}}